{
  "Version": 3,
  "Meta": {
    "PhysicsSettingCount": 3,
    "TotalInputCount": 8,
    "TotalOutputCount": 3,
    "VertexCount": 6,
    "EffectiveForces": {
      "Gravity": {
        "X": 0,
        "Y": -1
      },
      "Wind": {
        "X": 0,
        "Y": 0
      }
    },
    "PhysicsDictionary": [
      {
        "Id": "PhysicsSetting1",
        "Name": "Dummy1"
      },
      {
        "Id": "PhysicsSetting2",
        "Name": "Dummy2"
      },
      {
        "Id": "PhysicsSetting3",
        "Name": "Dummy3"
      }
    ]
  },
  "PhysicsSettings": [
    {
      "Id": "PhysicsSetting1",
      "Input": [
        {
          "Source": {
            "Target": "Parameter",
            "Id": "EyeTracking_ParamAngleX"
          },
          "Weight": 50,
          "Type": "X",
          "Reflect": false
        },
        {
          "Source": {
            "Target": "Parameter",
            "Id": "EyeTracking_ParamAngleY"
          },
          "Weight": 20,
          "Type": "X",
          "Reflect": false
        },
        {
          "Source": {
            "Target": "Parameter",
            "Id": "EyeTracking_ParamBodyUpperAngleX"
          },
          "Weight": 30,
          "Type": "X",
          "Reflect": false
        }
      ],
      "Output": [
        {
          "Destination": {
            "Target": "Parameter",
            "Id": "ParamYureHairFront"
          },
          "VertexIndex": 1,
          "Scale": 20,
          "Weight": 100,
          "Type": "Angle",
          "Reflect": false
        }
      ],
      "Vertices": [
        {
          "Position": {
            "X": 0,
            "Y": 0
          },
          "Mobility": 1,
          "Delay": 1,
          "Acceleration": 1,
          "Radius": 0
        },
        {
          "Position": {
            "X": 0,
            "Y": 7.4
          },
          "Mobility": 0.97,
          "Delay": 0.9,
          "Acceleration": 1.39,
          "Radius": 7.4
        }
      ],
      "Normalization": {
        "Position": {
          "Minimum": -10,
          "Default": 0,
          "Maximum": 10
        },
        "Angle": {
          "Minimum": -10,
          "Default": 0,
          "Maximum": 10
        }
      }
    },
    {
      "Id": "PhysicsSetting2",
      "Input": [
        {
          "Source": {
            "Target": "Parameter",
            "Id": "EyeTracking_ParamAngleX"
          },
          "Weight": 50,
          "Type": "X",
          "Reflect": false
        },
        {
          "Source": {
            "Target": "Parameter",
            "Id": "EyeTracking_ParamAngleY"
          },
          "Weight": 20,
          "Type": "X",
          "Reflect": false
        },
        {
          "Source": {
            "Target": "Parameter",
            "Id": "EyeTracking_ParamBodyUpperAngleX"
          },
          "Weight": 30,
          "Type": "X",
          "Reflect": false
        }
      ],
      "Output": [
        {
          "Destination": {
            "Target": "Parameter",
            "Id": "ParamYureHairSide"
          },
          "VertexIndex": 1,
          "Scale": 15,
          "Weight": 100,
          "Type": "Angle",
          "Reflect": false
        }
      ],
      "Vertices": [
        {
          "Position": {
            "X": 0,
            "Y": 0
          },
          "Mobility": 1,
          "Delay": 1,
          "Acceleration": 1,
          "Radius": 0
        },
        {
          "Position": {
            "X": 0,
            "Y": 8
          },
          "Mobility": 0.98,
          "Delay": 0.8,
          "Acceleration": 1.5,
          "Radius": 8
        }
      ],
      "Normalization": {
        "Position": {
          "Minimum": -10,
          "Default": 0,
          "Maximum": 10
        },
        "Angle": {
          "Minimum": -10,
          "Default": 0,
          "Maximum": 10
        }
      }
    },
    {
      "Id": "PhysicsSetting3",
      "Input": [
        {
          "Source": {
            "Target": "Parameter",
            "Id": "EyeTracking_ParamBodyUpperAngleX"
          },
          "Weight": 70,
          "Type": "X",
          "Reflect": false
        },
        {
          "Source": {
            "Target": "Parameter",
            "Id": "EyeTracking_ParamBodyUpperAngleY"
          },
          "Weight": 30,
          "Type": "X",
          "Reflect": false
        }
      ],
      "Output": [
        {
          "Destination": {
            "Target": "Parameter",
            "Id": "ParamYureParts"
          },
          "VertexIndex": 1,
          "Scale": 20,
          "Weight": 100,
          "Type": "Angle",
          "Reflect": false
        }
      ],
      "Vertices": [
        {
          "Position": {
            "X": 0,
            "Y": 0
          },
          "Mobility": 1,
          "Delay": 1,
          "Acceleration": 1,
          "Radius": 0
        },
        {
          "Position": {
            "X": 0,
            "Y": 5.7
          },
          "Mobility": 0.98,
          "Delay": 0.8,
          "Acceleration": 1.35,
          "Radius": 5.7
        }
      ],
      "Normalization": {
        "Position": {
          "Minimum": -10,
          "Default": 0,
          "Maximum": 10
        },
        "Angle": {
          "Minimum": -10,
          "Default": 0,
          "Maximum": 10
        }
      }
    }
  ]
}