{
  "Version": 3,
  "Meta": {
    "Duration": 6.0,
    "Fps": 60.0,
    "Loop": true,
    "AreBeziersRestricted": true,
    "CurveCount": 138,
    "TotalSegmentCount": 462,
    "TotalPointCount": 618,
    "UserDataCount": 1,
    "TotalUserDataSize": 0
  },
  "Curves": [
    {
      "Target": "Parameter",
      "Id": "EyeTracking_ParamAngleX",
      "Segments": [
        0,
        -15.511,
        0,
        1.133,
        -21,
        0,
        2.533,
        8.751,
        0,
        3.6,
        5.027,
        0,
        5.733,
        16.558,
        0,
        6,
        16
      ]
    },
    {
      "Target": "Parameter",
      "Id": "EyeTracking_ParamAngleY",
      "Segments": [
        0,
        -11.616,
        0,
        1.367,
        -12,
        1,
        1.739,
        -12,
        2.111,
        8.949,
        2.483,
        10.484,
        1,
        2.7,
        11.378,
        2.916,
        11.016,
        3.133,
        11.016,
        0,
        3.85,
        -1,
        0,
        5.267,
        0.842,
        0,
        6,
        -3
      ]
    },
    {
      "Target": "Parameter",
      "Id": "ParamAngleZ",
      "Segments": [
        0,
        0.9,
        0,
        1.3,
        0.616,
        0,
        2.533,
        2.842,
        1,
        2.678,
        2.842,
        2.822,
        2.961,
        2.967,
        2.57,
        1,
        3.378,
        1.454,
        3.789,
        -0.246,
        4.2,
        -0.246,
        0,
        5.233,
        0.204,
        0,
        6,
        -0.835
      ]
    },
    {
      "Target": "Parameter",
      "Id": "Param42",
      "Segments": [
        0,
        1.38,
        0,
        1.167,
        1.122,
        0,
        2.4,
        2.339,
        1,
        2.55,
        2.339,
        2.7,
        2.431,
        2.85,
        2.162,
        1,
        3.139,
        1.644,
        3.428,
        -0.149,
        3.717,
        -0.149,
        0,
        6,
        0.059
      ]
    },
    {
      "Target": "Parameter",
      "Id": "ParamEyeLOpen",
      "Segments": [
        0,
        0,
        2,
        1.367,
        0,
        1,
        1.478,
        0,
        1.589,
        0.128,
        1.7,
        0.4,
        1,
        1.861,
        0.794,
        2.022,
        1,
        2.183,
        1,
        0,
        4,
        0.6,
        2,
        4.8,
        0.6,
        0,
        5.217,
        0,
        2,
        6,
        0
      ]
    },
    {
      "Target": "Parameter",
      "Id": "ParamEyeLSmile",
      "Segments": [
        0,
        0,
        2,
        3.2,
        0,
        0,
        3.833,
        1,
        0,
        6,
        0.893
      ]
    },
    {
      "Target": "Parameter",
      "Id": "ParamEyeROpen",
      "Segments": [
        0,
        0,
        2,
        1.367,
        0,
        1,
        1.478,
        0,
        1.589,
        0.128,
        1.7,
        0.4,
        1,
        1.861,
        0.794,
        2.022,
        1,
        2.183,
        1,
        0,
        4,
        0.6,
        2,
        4.8,
        0.6,
        0,
        5.217,
        0,
        2,
        6,
        0
      ]
    },
    {
      "Target": "Parameter",
      "Id": "ParamEyeRSmile",
      "Segments": [
        0,
        0,
        2,
        3.2,
        0,
        0,
        3.833,
        1,
        0,
        6,
        0.893
      ]
    },
    {
      "Target": "Parameter",
      "Id": "EyeTracking_ParamEyeBallX",
      "Segments": [
        0,
        -0.203,
        0,
        6,
        0.1
      ]
    },
    {
      "Target": "Parameter",
      "Id": "EyeTracking_ParamEyeBallY",
      "Segments": [
        0,
        -0.838,
        1,
        0.456,
        -0.838,
        0.911,
        -0.762,
        1.367,
        -0.3,
        1,
        1.639,
        -0.024,
        1.911,
        0.5,
        2.183,
        0.5,
        2,
        6,
        0.5
      ]
    },
    {
      "Target": "Parameter",
      "Id": "ParamBrowLY",
      "Segments": [
        0,
        -0.6,
        2,
        2.683,
        -0.6,
        0,
        6,
        -0.9
      ]
    },
    {
      "Target": "Parameter",
      "Id": "ParamBrowLForm",
      "Segments": [
        0,
        -0.7,
        2,
        2.667,
        -0.7,
        0,
        4.133,
        -0.4,
        2,
        6,
        -0.4
      ]
    },
    {
      "Target": "Parameter",
      "Id": "ParamBrowRY",
      "Segments": [
        0,
        -0.6,
        2,
        2.683,
        -0.6,
        0,
        6,
        -0.9
      ]
    },
    {
      "Target": "Parameter",
      "Id": "ParamBrowRForm",
      "Segments": [
        0,
        -0.7,
        2,
        2.667,
        -0.7,
        0,
        4.133,
        -0.4,
        2,
        6,
        -0.4
      ]
    },
    {
      "Target": "Parameter",
      "Id": "ParamMouthForm",
      "Segments": [
        0,
        0,
        0,
        6,
        1
      ]
    },
    {
      "Target": "Parameter",
      "Id": "ParamMouthOpenY",
      "Segments": [
        0,
        0,
        2,
        1.467,
        0,
        0,
        2.133,
        0.3,
        0,
        3.117,
        0,
        2,
        6,
        0
      ]
    },
    {
      "Target": "Parameter",
      "Id": "ParamMouthSize",
      "Segments": [
        0,
        0,
        0,
        1.467,
        0.7,
        1,
        1.7,
        0.7,
        1.934,
        -0.29,
        2.167,
        -0.3,
        1,
        3.1,
        -0.342,
        4.034,
        -0.355,
        4.967,
        -0.4,
        1,
        5.311,
        -0.417,
        5.656,
        -1,
        6,
        -1
      ]
    },
    {
      "Target": "Parameter",
      "Id": "ParamCheek",
      "Segments": [
        0,
        0,
        2,
        5.033,
        0,
        0,
        5.65,
        1,
        2,
        6,
        1
      ]
    },
    {
      "Target": "Parameter",
      "Id": "ParamHairSideL1",
      "Segments": [
        0,
        0.008,
        0,
        1.4,
        -10,
        0,
        2.467,
        8,
        0,
        3.583,
        -7.211,
        0,
        4.983,
        2.865,
        0,
        6,
        1.456
      ]
    },
    {
      "Target": "Parameter",
      "Id": "ParamHairSideL2",
      "Segments": [
        0,
        0.9,
        0,
        1.883,
        -8,
        0,
        3.05,
        7.937,
        0,
        4.2,
        -6.567,
        0,
        5.4,
        7.272,
        0,
        6,
        5.575
      ]
    },
    {
      "Target": "Parameter",
      "Id": "Param3",
      "Segments": [
        0,
        0.021,
        0,
        1.4,
        -8,
        0,
        2.467,
        9,
        0,
        3.4,
        -5.36,
        0,
        4.867,
        6.105,
        0,
        6,
        3.816
      ]
    },
    {
      "Target": "Parameter",
      "Id": "Param2",
      "Segments": [
        0,
        0.849,
        0,
        1.85,
        -8,
        0,
        2.917,
        8,
        0,
        3.85,
        -3.141,
        0,
        5.183,
        8,
        0,
        6,
        6.269
      ]
    },
    {
      "Target": "Parameter",
      "Id": "ParamHairFront1",
      "Segments": [
        0,
        0,
        0,
        0.483,
        0.933,
        0,
        1.467,
        -11,
        0,
        2.5,
        9,
        0,
        3.45,
        -7.142,
        0,
        4.7,
        5.539,
        0,
        6,
        0
      ]
    },
    {
      "Target": "Parameter",
      "Id": "ParamHairFront2",
      "Segments": [
        0,
        -0.418,
        0,
        0.867,
        0.933,
        0,
        1.85,
        -12,
        0,
        2.85,
        7.689,
        0,
        3.833,
        -9.142,
        0,
        5.033,
        2.618,
        0,
        6,
        -5.139
      ]
    },
    {
      "Target": "Parameter",
      "Id": "ParamHairSideR1",
      "Segments": [
        0,
        0.003,
        1,
        0.467,
        0.003,
        0.933,
        -6.441,
        1.4,
        -14.62,
        1,
        1.622,
        -18.515,
        1.845,
        -18.998,
        2.067,
        -18.998,
        0,
        3.167,
        13.44,
        0,
        4.183,
        -28.148,
        0,
        4.983,
        8.491,
        0,
        5.45,
        0.664,
        0,
        6,
        2
      ]
    },
    {
      "Target": "Parameter",
      "Id": "ParamHairSideR2",
      "Segments": [
        0,
        0.307,
        1,
        0.567,
        0.307,
        1.133,
        -7.435,
        1.7,
        -15.62,
        1,
        1.928,
        -18.91,
        2.155,
        -18.776,
        2.383,
        -18.776,
        0,
        3.583,
        15.463,
        0,
        4.517,
        -29.512,
        0,
        5.25,
        -0.347,
        0,
        5.667,
        -6.35,
        0,
        6,
        -4.88
      ]
    },
    {
      "Target": "Parameter",
      "Id": "ParamHairBack1",
      "Segments": [
        0,
        0.01,
        0,
        1.3,
        -9,
        0,
        2.483,
        8,
        0,
        3.683,
        -11.459,
        0,
        5.083,
        -2.031,
        0,
        6,
        -3.726
      ]
    },
    {
      "Target": "Parameter",
      "Id": "ParamHairBack2",
      "Segments": [
        0,
        0.386,
        0,
        1.8,
        -8,
        0,
        2.983,
        7,
        0,
        4.183,
        -9.459,
        0,
        5.5,
        -0.547,
        0,
        6,
        -2.097
      ]
    },
    {
      "Target": "Parameter",
      "Id": "Param5",
      "Segments": [
        0,
        14,
        0,
        1.433,
        24.674,
        0,
        2.467,
        -5.222,
        0,
        4.167,
        22.638,
        0,
        5.417,
        7.988,
        1,
        5.611,
        7.988,
        5.806,
        8.895,
        6,
        8.993
      ]
    },
    {
      "Target": "Parameter",
      "Id": "Param6",
      "Segments": [
        0,
        16.345,
        0,
        1.917,
        25.674,
        0,
        2.8,
        -4.222,
        0,
        4.7,
        20.983,
        0,
        5.65,
        4.744,
        0,
        6,
        5.913
      ]
    },
    {
      "Target": "Parameter",
      "Id": "Param4",
      "Segments": [
        0,
        -14.169,
        0,
        1.283,
        -24,
        0,
        2.583,
        16,
        0,
        3.533,
        -9,
        0,
        6,
        0
      ]
    },
    {
      "Target": "Parameter",
      "Id": "Param8",
      "Segments": [
        0,
        0,
        0,
        1.1,
        -14,
        0,
        2.233,
        10,
        0,
        3.467,
        -16.268,
        0,
        4.8,
        7.077,
        0,
        6,
        0
      ]
    },
    {
      "Target": "Parameter",
      "Id": "Param9",
      "Segments": [
        0,
        -0.101,
        0,
        1.567,
        -20,
        0,
        2.7,
        9,
        0,
        3.933,
        -16.268,
        0,
        5.15,
        7.913,
        0,
        6,
        -1.246
      ]
    },
    {
      "Target": "Parameter",
      "Id": "EyeTracking_ParamBodyUpperAngleX",
      "Segments": [
        0,
        -26.809,
        0,
        1.533,
        -28,
        0,
        3.533,
        2.199,
        0,
        5.033,
        -4.797,
        0,
        6,
        -2.83
      ]
    },
    {
      "Target": "Parameter",
      "Id": "ParamBodyLowerAngleX",
      "Segments": [
        0,
        -0.004,
        0,
        1.117,
        -11,
        0,
        2.517,
        6,
        0,
        4.567,
        -3.185,
        0,
        6,
        -0.756
      ]
    },
    {
      "Target": "Parameter",
      "Id": "EyeTracking_ParamBodyUpperAngleY",
      "Segments": [
        0,
        -13.257,
        0,
        0.767,
        -18,
        1,
        1.039,
        -18,
        1.311,
        -13.774,
        1.583,
        -8,
        1,
        1.922,
        -0.812,
        2.261,
        1.744,
        2.6,
        1.744,
        0,
        3.167,
        -4.588,
        0,
        6,
        0
      ]
    },
    {
      "Target": "Parameter",
      "Id": "ParamBodyLowerAngleY",
      "Segments": [
        0,
        -5.935,
        0,
        0.767,
        -15.98,
        1,
        1.039,
        -15.98,
        1.311,
        1.671,
        1.583,
        2.629,
        1,
        2,
        4.096,
        2.416,
        4.008,
        2.833,
        4.008,
        1,
        3.016,
        4.008,
        3.2,
        2.791,
        3.383,
        -1.653,
        1,
        3.533,
        -5.289,
        3.683,
        -8.658,
        3.833,
        -8.658,
        0,
        4.817,
        5.165,
        0,
        6,
        -0.228
      ]
    },
    {
      "Target": "Parameter",
      "Id": "ParamBodyUpperAngleZ",
      "Segments": [
        0,
        -2.477,
        0,
        1.067,
        -3.191,
        0,
        2.833,
        -1.371,
        0,
        4.317,
        -2.574,
        0,
        5.283,
        -1.977,
        0,
        6,
        -2.107
      ]
    },
    {
      "Target": "Parameter",
      "Id": "ParamBodyLowerAngleZ",
      "Segments": [
        0,
        -3.29,
        0,
        0.767,
        -4.18,
        0,
        2.517,
        -1.634,
        0,
        4,
        -2.928,
        0,
        4.967,
        -2.247,
        0,
        6,
        -2.411
      ]
    },
    {
      "Target": "Parameter",
      "Id": "Param39",
      "Segments": [
        0,
        0,
        2,
        3.133,
        0,
        1,
        3.628,
        0,
        4.122,
        -3.859,
        4.617,
        -5,
        1,
        5.078,
        -6.064,
        5.539,
        -5.936,
        6,
        -5.936
      ]
    },
    {
      "Target": "Parameter",
      "Id": "Param",
      "Segments": [
        0,
        0,
        2,
        3.133,
        0,
        1,
        3.628,
        0,
        4.122,
        2.714,
        4.617,
        3,
        1,
        5.078,
        3.266,
        5.539,
        3.208,
        6,
        3.208
      ]
    },
    {
      "Target": "Parameter",
      "Id": "ParamShoulderL",
      "Segments": [
        0,
        -0.003,
        0,
        1.133,
        8,
        0,
        2.517,
        -5,
        0,
        6,
        -0.139
      ]
    },
    {
      "Target": "Parameter",
      "Id": "ParamShoulderR",
      "Segments": [
        0,
        -0.003,
        0,
        1.133,
        8,
        0,
        2.517,
        -5,
        0,
        6,
        -0.139
      ]
    },
    {
      "Target": "Parameter",
      "Id": "ParamBreath",
      "Segments": [
        0,
        0.8,
        0,
        1.333,
        0,
        0,
        2.95,
        0.9,
        0,
        6,
        0.7
      ]
    },
    {
      "Target": "Parameter",
      "Id": "ParamBustX",
      "Segments": [
        0,
        -0.118,
        0,
        0.817,
        -8,
        0,
        2.333,
        9,
        0,
        3.6,
        -10.115,
        0,
        4.85,
        2.644,
        0,
        6,
        -3.264
      ]
    },
    {
      "Target": "Parameter",
      "Id": "ParamBustY",
      "Segments": [
        0,
        -0.083,
        0,
        0.617,
        14,
        0,
        1.65,
        -10,
        0,
        3.083,
        12,
        0,
        3.9,
        -14.976,
        0,
        5.05,
        0.724,
        0,
        6,
        -2.72
      ]
    },
    {
      "Target": "Parameter",
      "Id": "Param22",
      "Segments": [
        0,
        0,
        0,
        0.783,
        -6,
        0,
        2.067,
        8,
        0,
        3.283,
        -7.777,
        0,
        4.933,
        4,
        0,
        6,
        -0.707
      ]
    },
    {
      "Target": "Parameter",
      "Id": "Param23",
      "Segments": [
        0,
        -0.269,
        0,
        1.4,
        -9,
        0,
        2.55,
        8,
        0,
        3.767,
        -8.797,
        0,
        5.267,
        0.733,
        0,
        6,
        -3.756
      ]
    },
    {
      "Target": "Parameter",
      "Id": "Param18",
      "Segments": [
        0,
        0,
        0,
        1.05,
        8,
        0,
        2.283,
        -7,
        0,
        3.283,
        11.791,
        0,
        4.883,
        1.016,
        0,
        6,
        1.817
      ]
    },
    {
      "Target": "Parameter",
      "Id": "Param19",
      "Segments": [
        0,
        0.686,
        0,
        1.567,
        10,
        0,
        2.8,
        -7,
        0,
        3.8,
        12.532,
        0,
        5.133,
        2.426,
        0,
        6,
        3.47
      ]
    },
    {
      "Target": "Parameter",
      "Id": "Param24",
      "Segments": [
        0,
        7,
        0,
        0.8,
        -5,
        0,
        2.433,
        12.471,
        0,
        3.45,
        0.573,
        0,
        4.9,
        10.023,
        0,
        6,
        7.981
      ]
    },
    {
      "Target": "Parameter",
      "Id": "Param25",
      "Segments": [
        0,
        9.982,
        0,
        1.383,
        1,
        0,
        2.883,
        11.372,
        0,
        3.733,
        0.252,
        0,
        5.3,
        8.116,
        0,
        6,
        7.04
      ]
    },
    {
      "Target": "Parameter",
      "Id": "Param20",
      "Segments": [
        0,
        -7,
        0,
        0.867,
        1,
        0,
        2.7,
        -10.097,
        0,
        3.583,
        7.557,
        0,
        4.867,
        -7.372,
        0,
        6,
        -6.752
      ]
    },
    {
      "Target": "Parameter",
      "Id": "Param21",
      "Segments": [
        0,
        -9.566,
        0,
        1.517,
        0,
        0,
        3.15,
        -9.097,
        0,
        3.917,
        8.222,
        0,
        5.15,
        -6.523,
        0,
        6,
        -5.697
      ]
    },
    {
      "Target": "Parameter",
      "Id": "ParamArmUpperLZ",
      "Segments": [
        0,
        8,
        0,
        0.75,
        11,
        0,
        1.583,
        7.22,
        0,
        2.6,
        13.58,
        0,
        3.8,
        12.461,
        0,
        4.883,
        13.324,
        0,
        6,
        13
      ]
    },
    {
      "Target": "Parameter",
      "Id": "ParamArmUpperLX",
      "Segments": [
        0,
        0,
        0,
        0.883,
        11.192,
        0,
        2.133,
        -11,
        0,
        3.15,
        9,
        0,
        4.683,
        -3.271,
        0,
        6,
        -0.753
      ]
    },
    {
      "Target": "Parameter",
      "Id": "ParamArmUpperLY",
      "Segments": [
        0,
        0,
        0,
        1.1,
        0.38,
        0,
        3.083,
        -0.203,
        0,
        4.667,
        0.18,
        0,
        6,
        0.05
      ]
    },
    {
      "Target": "Parameter",
      "Id": "ParamArmLowerLZ",
      "Segments": [
        0,
        -21.06,
        0,
        0.85,
        -20.671,
        1,
        1.128,
        -20.671,
        1.405,
        -20.639,
        1.683,
        -21.06,
        1,
        1.939,
        -21.447,
        2.194,
        -22.854,
        2.45,
        -22.854,
        1,
        2.844,
        -22.854,
        3.239,
        -13.876,
        3.633,
        -11.093,
        1,
        3.983,
        -8.623,
        4.333,
        -8.939,
        4.683,
        -8.939,
        0,
        6,
        -10
      ]
    },
    {
      "Target": "Parameter",
      "Id": "ParamArmLowerLX",
      "Segments": [
        0,
        0,
        0,
        0.833,
        15,
        0,
        2.25,
        -12,
        0,
        3.667,
        3.047,
        0,
        6,
        -2.571
      ]
    },
    {
      "Target": "Parameter",
      "Id": "ParamArmLowerLY",
      "Segments": [
        0,
        9.85,
        0,
        1.117,
        1.297,
        0,
        2.25,
        3.012,
        0,
        3.617,
        0.038,
        0,
        6,
        0.771
      ]
    },
    {
      "Target": "Parameter",
      "Id": "Param40",
      "Segments": [
        0,
        -0.036,
        0,
        1.1,
        12,
        0,
        1.967,
        -8,
        0,
        3.15,
        11.63,
        0,
        4.933,
        -3.996,
        0,
        6,
        -0.677
      ]
    },
    {
      "Target": "Parameter",
      "Id": "Param41",
      "Segments": [
        0,
        -0.869,
        0,
        1.517,
        14,
        0,
        2.383,
        -8,
        0,
        3.567,
        12.63,
        0,
        4.933,
        -2.022,
        0,
        6,
        1.021
      ]
    },
    {
      "Target": "Parameter",
      "Id": "ParamArmHandLZ",
      "Segments": [
        0,
        -2,
        0,
        0.583,
        -3.675,
        0,
        1.383,
        -1,
        0,
        2.95,
        -7.393,
        0,
        4.383,
        3.506,
        0,
        5.417,
        -1,
        0,
        6,
        -0.394
      ]
    },
    {
      "Target": "Parameter",
      "Id": "ParamArmHandLX",
      "Segments": [
        0,
        20.24,
        1,
        0.25,
        20.24,
        0.5,
        5.034,
        0.75,
        5,
        1,
        2.5,
        4.76,
        4.25,
        4.685,
        6,
        4.685
      ]
    },
    {
      "Target": "Parameter",
      "Id": "Param13",
      "Segments": [
        0,
        -30,
        2,
        0.75,
        -30,
        0,
        2.067,
        -5,
        0,
        3.667,
        -30,
        0,
        6,
        -1.563
      ]
    },
    {
      "Target": "Parameter",
      "Id": "Param12",
      "Segments": [
        0,
        -19,
        0,
        0.75,
        -22,
        0,
        2.067,
        4,
        0,
        3.667,
        -18,
        0,
        6,
        0
      ]
    },
    {
      "Target": "Parameter",
      "Id": "ParamArmUpperRZ",
      "Segments": [
        0,
        15.44,
        1,
        0.256,
        15.44,
        0.511,
        16.103,
        0.767,
        16.362,
        1,
        1.156,
        16.756,
        1.544,
        16.79,
        1.933,
        16.79,
        0,
        3.333,
        -3.56,
        1,
        3.6,
        -3.56,
        3.866,
        -2.223,
        4.133,
        -2,
        1,
        4.755,
        -1.479,
        5.378,
        -1.415,
        6,
        -1.415
      ]
    },
    {
      "Target": "Parameter",
      "Id": "ParamArmUpperRY",
      "Segments": [
        0,
        0,
        1,
        1.017,
        0,
        2.033,
        5.882,
        3.05,
        19,
        1,
        3.3,
        22.226,
        3.55,
        24.66,
        3.8,
        24.66,
        0,
        4.733,
        18.559,
        0,
        6,
        19.053
      ]
    },
    {
      "Target": "Parameter",
      "Id": "ParamArmLowerRZ",
      "Segments": [
        0,
        -15.46,
        0,
        1.133,
        -15.842,
        1,
        1.566,
        -15.842,
        2,
        -15.853,
        2.433,
        -15.182,
        1,
        2.672,
        -14.812,
        2.911,
        -1.914,
        3.15,
        -1.914,
        0,
        4.233,
        -5.009,
        1,
        4.544,
        -5.009,
        4.856,
        -2.395,
        5.167,
        -1.105,
        1,
        5.445,
        0.047,
        5.722,
        0,
        6,
        0
      ]
    },
    {
      "Target": "Parameter",
      "Id": "ParamArmLowerRX",
      "Segments": [
        0,
        0,
        0,
        2.917,
        9,
        0,
        3.767,
        -2.735,
        0,
        6,
        0
      ]
    },
    {
      "Target": "Parameter",
      "Id": "ParamArmLowerRY",
      "Segments": [
        0,
        0,
        0,
        2.233,
        5,
        1,
        2.566,
        5,
        2.9,
        1.648,
        3.233,
        -6.383,
        1,
        3.422,
        -10.934,
        3.611,
        -14,
        3.8,
        -14,
        0,
        5.25,
        0.548,
        0,
        6,
        0
      ]
    },
    {
      "Target": "Parameter",
      "Id": "ParamArmHandRZ",
      "Segments": [
        0,
        0,
        0,
        2.633,
        -8.749,
        1,
        2.772,
        -8.749,
        2.911,
        -6.99,
        3.05,
        3.151,
        1,
        3.144,
        10.047,
        3.239,
        22.44,
        3.333,
        22.44,
        0,
        4.85,
        7.639,
        0,
        5.517,
        23.336,
        0,
        6,
        21.878
      ]
    },
    {
      "Target": "Parameter",
      "Id": "ParamArmHandRX",
      "Segments": [
        0,
        0,
        0,
        1.95,
        1,
        0,
        2.85,
        -20.66,
        0,
        3.6,
        24.827,
        0,
        4.25,
        -11.939,
        0,
        5.117,
        11.683,
        0,
        6,
        9
      ]
    },
    {
      "Target": "Parameter",
      "Id": "Param14",
      "Segments": [
        0,
        29.04,
        1,
        1.011,
        29.04,
        2.022,
        28.376,
        3.033,
        26,
        1,
        3.233,
        25.53,
        3.433,
        20.352,
        3.633,
        20.352,
        0,
        4.133,
        30,
        0,
        6,
        29.742
      ]
    },
    {
      "Target": "Parameter",
      "Id": "Param15",
      "Segments": [
        0,
        8.358,
        1,
        0.989,
        8.358,
        1.978,
        5.126,
        2.967,
        -1,
        1,
        3.184,
        -2.342,
        3.4,
        -2.86,
        3.617,
        -2.86,
        1,
        3.789,
        -2.86,
        3.961,
        18.48,
        4.133,
        19,
        1,
        4.755,
        20.879,
        5.378,
        21.233,
        6,
        21.233
      ]
    },
    {
      "Target": "Parameter",
      "Id": "Param17",
      "Segments": [
        0,
        20,
        1,
        1.378,
        20,
        2.755,
        -10.848,
        4.133,
        -15,
        1,
        4.755,
        -16.875,
        5.378,
        -16,
        6,
        -16
      ]
    },
    {
      "Target": "Parameter",
      "Id": "Param16",
      "Segments": [
        0,
        -30,
        0,
        3.033,
        -21,
        0,
        4.133,
        -30,
        2,
        6,
        -30
      ]
    },
    {
      "Target": "Parameter",
      "Id": "Param43",
      "Segments": [
        0,
        -2,
        0,
        6,
        0
      ]
    },
    {
      "Target": "Parameter",
      "Id": "Param44",
      "Segments": [
        0,
        -1.26,
        0,
        6,
        0
      ]
    },
    {
      "Target": "Parameter",
      "Id": "Param47",
      "Segments": [
        0,
        4.324,
        0,
        6,
        0
      ]
    },
    {
      "Target": "Parameter",
      "Id": "Param45",
      "Segments": [
        0,
        4,
        0,
        6,
        0
      ]
    },
    {
      "Target": "Parameter",
      "Id": "Param35",
      "Segments": [
        0,
        0,
        0,
        0.75,
        4,
        0,
        3.367,
        0,
        2,
        6,
        0
      ]
    },
    {
      "Target": "Parameter",
      "Id": "Param36",
      "Segments": [
        0,
        -4.86,
        0,
        6,
        0
      ]
    },
    {
      "Target": "Parameter",
      "Id": "ParamLegUpperLZ",
      "Segments": [
        0,
        0,
        0,
        0.767,
        -2.76,
        1,
        1.134,
        -2.76,
        1.5,
        3.631,
        1.867,
        3.94,
        1,
        2.345,
        4.343,
        2.822,
        4.293,
        3.3,
        4.293,
        1,
        3.617,
        4.293,
        3.933,
        1.536,
        4.25,
        1.358,
        1,
        4.822,
        1.036,
        5.395,
        1.036,
        5.967,
        1.036,
        2,
        6,
        1.036
      ]
    },
    {
      "Target": "Parameter",
      "Id": "ParamLegUpperLX",
      "Segments": [
        0,
        0,
        0,
        0.8,
        -6.888,
        1,
        1.161,
        -6.888,
        1.522,
        3.26,
        1.883,
        4,
        1,
        2.322,
        4.899,
        2.761,
        4.777,
        3.2,
        4.777,
        0,
        4.15,
        -1.423,
        0,
        6,
        0
      ]
    },
    {
      "Target": "Parameter",
      "Id": "ParamLegUpperLY",
      "Segments": [
        0,
        0,
        0,
        0.767,
        -5.76,
        0,
        1.867,
        -2,
        0,
        6,
        -2.76
      ]
    },
    {
      "Target": "Parameter",
      "Id": "ParamLegLowerLZ",
      "Segments": [
        0,
        0,
        0,
        0.767,
        4.08,
        0,
        1.867,
        -12.48,
        1,
        2.345,
        -12.48,
        2.822,
        -12.531,
        3.3,
        -11.603,
        1,
        3.611,
        -10.999,
        3.922,
        -2.006,
        4.233,
        -2.006,
        1,
        4.516,
        -2.006,
        4.8,
        -4.765,
        5.083,
        -5.629,
        1,
        5.389,
        -6.561,
        5.694,
        -6.506,
        6,
        -6.506
      ]
    },
    {
      "Target": "Parameter",
      "Id": "ParamLegFootLZ",
      "Segments": [
        0,
        0,
        0,
        0.767,
        -7.14,
        1,
        1.139,
        -7.14,
        1.511,
        -0.347,
        1.883,
        0,
        1,
        2.455,
        0.534,
        3.028,
        0.517,
        3.6,
        1,
        1,
        3.883,
        1.239,
        4.167,
        5,
        4.45,
        5,
        1,
        4.967,
        5,
        5.483,
        4.016,
        6,
        3.954
      ]
    },
    {
      "Target": "Parameter",
      "Id": "Param29",
      "Segments": [
        0,
        0,
        0,
        0.683,
        10,
        0,
        2,
        -9,
        1,
        2.361,
        -9,
        2.722,
        7.408,
        3.083,
        10.496,
        1,
        3.494,
        14.012,
        3.906,
        13.683,
        4.317,
        13.683,
        0,
        5.217,
        -2.237,
        0,
        6,
        0
      ]
    },
    {
      "Target": "Parameter",
      "Id": "Param31",
      "Segments": [
        0,
        -0.311,
        0,
        1.333,
        14,
        0,
        2.517,
        -10,
        1,
        2.878,
        -10,
        3.239,
        8.249,
        3.6,
        10.496,
        1,
        3.994,
        12.951,
        4.389,
        12.598,
        4.783,
        12.598,
        0,
        5.633,
        -4.128,
        0,
        6,
        -1.865
      ]
    },
    {
      "Target": "Parameter",
      "Id": "Param33",
      "Segments": [
        0,
        0,
        0,
        1.067,
        -17,
        1,
        1.406,
        -17,
        1.744,
        7.89,
        2.083,
        17,
        1,
        2.383,
        25.064,
        2.683,
        24.458,
        2.983,
        24.458,
        0,
        4.05,
        -18.978,
        0,
        4.983,
        4.5,
        0,
        6,
        0
      ]
    },
    {
      "Target": "Parameter",
      "Id": "ParamLegUpperRY",
      "Segments": [
        0,
        0,
        0,
        0.767,
        -9.18,
        0,
        2.3,
        0,
        0,
        3.817,
        -5.04,
        0,
        4.983,
        0,
        2,
        6,
        0
      ]
    },
    {
      "Target": "Parameter",
      "Id": "ParamLegLowerRY",
      "Segments": [
        0,
        0,
        0,
        0.767,
        -5.46,
        0,
        2.3,
        0,
        0,
        3.817,
        -3.18,
        0,
        4.983,
        0,
        2,
        6,
        0
      ]
    },
    {
      "Target": "Parameter",
      "Id": "Param30",
      "Segments": [
        0,
        0,
        0,
        0.817,
        8,
        0,
        2.317,
        -11,
        0,
        4.05,
        6,
        0,
        5.167,
        -8,
        0,
        6,
        -4.244
      ]
    },
    {
      "Target": "Parameter",
      "Id": "Param32",
      "Segments": [
        0,
        -0.499,
        0,
        1.45,
        11,
        0,
        2.95,
        -10,
        0,
        4.5,
        7,
        0,
        5.517,
        -7,
        0,
        6,
        -3.429
      ]
    },
    {
      "Target": "Parameter",
      "Id": "ParamSizeCheck",
      "Segments": [
        0,
        0,
        0,
        6,
        0
      ]
    },
    {
      "Target": "Parameter",
      "Id": "ParamBrowLAngle",
      "Segments": [
        0,
        0,
        0,
        6,
        0
      ]
    },
    {
      "Target": "Parameter",
      "Id": "ParamBrowRAngle",
      "Segments": [
        0,
        0,
        0,
        6,
        0
      ]
    },
    {
      "Target": "Parameter",
      "Id": "Param7",
      "Segments": [
        0,
        30,
        0,
        6,
        30
      ]
    },
    {
      "Target": "Parameter",
      "Id": "Param55",
      "Segments": [
        0,
        0,
        0,
        6,
        0
      ]
    },
    {
      "Target": "Parameter",
      "Id": "Param56",
      "Segments": [
        0,
        0,
        0,
        6,
        0
      ]
    },
    {
      "Target": "Parameter",
      "Id": "ParamArmHandLY",
      "Segments": [
        0,
        0,
        0,
        6,
        0
      ]
    },
    {
      "Target": "Parameter",
      "Id": "Param34",
      "Segments": [
        0,
        0,
        0,
        6,
        0
      ]
    },
    {
      "Target": "Parameter",
      "Id": "ParamArmUpperRX",
      "Segments": [
        0,
        0,
        0,
        6,
        0
      ]
    },
    {
      "Target": "Parameter",
      "Id": "Param50",
      "Segments": [
        0,
        30,
        0,
        6,
        30
      ]
    },
    {
      "Target": "Parameter",
      "Id": "ParamArmHandRY",
      "Segments": [
        0,
        0,
        0,
        6,
        0
      ]
    },
    {
      "Target": "Parameter",
      "Id": "Param10",
      "Segments": [
        0,
        0,
        0,
        6,
        0
      ]
    },
    {
      "Target": "Parameter",
      "Id": "Param46",
      "Segments": [
        0,
        0,
        0,
        6,
        0
      ]
    },
    {
      "Target": "Parameter",
      "Id": "Param59",
      "Segments": [
        0,
        0,
        0,
        6,
        0
      ]
    },
    {
      "Target": "Parameter",
      "Id": "Param58",
      "Segments": [
        0,
        0,
        0,
        6,
        0
      ]
    },
    {
      "Target": "Parameter",
      "Id": "Param11",
      "Segments": [
        0,
        0,
        0,
        6,
        0
      ]
    },
    {
      "Target": "Parameter",
      "Id": "Param48",
      "Segments": [
        0,
        0,
        0,
        6,
        0
      ]
    },
    {
      "Target": "Parameter",
      "Id": "Param54",
      "Segments": [
        0,
        0,
        0,
        6,
        0
      ]
    },
    {
      "Target": "Parameter",
      "Id": "Param53",
      "Segments": [
        0,
        0,
        0,
        6,
        0
      ]
    },
    {
      "Target": "Parameter",
      "Id": "Param52",
      "Segments": [
        0,
        0,
        0,
        6,
        0
      ]
    },
    {
      "Target": "Parameter",
      "Id": "Param49",
      "Segments": [
        0,
        0,
        0,
        6,
        0
      ]
    },
    {
      "Target": "Parameter",
      "Id": "Param38",
      "Segments": [
        0,
        0,
        0,
        6,
        0
      ]
    },
    {
      "Target": "Parameter",
      "Id": "Param51",
      "Segments": [
        0,
        0,
        0,
        6,
        0
      ]
    },
    {
      "Target": "Parameter",
      "Id": "Param27",
      "Segments": [
        0,
        0,
        0,
        6,
        0
      ]
    },
    {
      "Target": "Parameter",
      "Id": "Param26",
      "Segments": [
        0,
        0,
        0,
        6,
        0
      ]
    },
    {
      "Target": "Parameter",
      "Id": "Param28",
      "Segments": [
        0,
        0,
        0,
        6,
        0
      ]
    },
    {
      "Target": "Parameter",
      "Id": "Param37",
      "Segments": [
        0,
        0,
        0,
        6,
        0
      ]
    },
    {
      "Target": "Parameter",
      "Id": "ParamLegLowerLX",
      "Segments": [
        0,
        0,
        0,
        6,
        0
      ]
    },
    {
      "Target": "Parameter",
      "Id": "ParamLegLowerLY",
      "Segments": [
        0,
        0,
        0,
        6,
        0
      ]
    },
    {
      "Target": "Parameter",
      "Id": "ParamLegFootLX",
      "Segments": [
        0,
        0,
        0,
        6,
        0
      ]
    },
    {
      "Target": "Parameter",
      "Id": "ParamLegFootLY",
      "Segments": [
        0,
        0,
        0,
        6,
        0
      ]
    },
    {
      "Target": "Parameter",
      "Id": "ParamLegUpperRZ",
      "Segments": [
        0,
        0,
        0,
        6,
        0
      ]
    },
    {
      "Target": "Parameter",
      "Id": "ParamLegUpperRX",
      "Segments": [
        0,
        0,
        0,
        6,
        0
      ]
    },
    {
      "Target": "Parameter",
      "Id": "ParamLegLowerRZ",
      "Segments": [
        0,
        0,
        0,
        6,
        0
      ]
    },
    {
      "Target": "Parameter",
      "Id": "ParamLegLowerRX",
      "Segments": [
        0,
        0,
        0,
        6,
        0
      ]
    },
    {
      "Target": "Parameter",
      "Id": "ParamLegFootRZ",
      "Segments": [
        0,
        0,
        0,
        6,
        0
      ]
    },
    {
      "Target": "Parameter",
      "Id": "ParamLegFootRX",
      "Segments": [
        0,
        0,
        0,
        6,
        0
      ]
    },
    {
      "Target": "Parameter",
      "Id": "ParamLegFootRY",
      "Segments": [
        0,
        0,
        0,
        6,
        0
      ]
    },
    {
      "Target": "Parameter",
      "Id": "ParamYureHairFront",
      "Segments": [
        0,
        0,
        0,
        6,
        0
      ]
    },
    {
      "Target": "Parameter",
      "Id": "ParamYureHairSide",
      "Segments": [
        0,
        0,
        0,
        6,
        0
      ]
    },
    {
      "Target": "Parameter",
      "Id": "ParamYureParts",
      "Segments": [
        0,
        0,
        0,
        6,
        0
      ]
    },
    {
      "Target": "Parameter",
      "Id": "ParamYureBust",
      "Segments": [
        0,
        0,
        0,
        6,
        0
      ]
    },
    {
      "Target": "Parameter",
      "Id": "Param57",
      "Segments": [
        0,
        0,
        0,
        6,
        0
      ]
    }
  ],
  "UserData": [
    {
      "Time": 0.0,
      "Value": ""
    }
  ]
}